ijsoned/__init__.py
ijsoned/ijsoned.py
ijsoned-0.1.0.dist-info/LICENSE
ijsoned-0.1.0.dist-info/METADATA
ijsoned-0.1.0.dist-info/WHEEL
ijsoned-0.1.0.dist-info/entry_points.txt
ijsoned-0.1.0.dist-info/top_level.txt
ijsoned-0.1.0.dist-info/RECORD
