Metadata-Version: 2.1
Name: ijsoned
Version: 0.1.0
Summary: Interactive json editor
Author-email: Michael White <ijsoned@mypalmike.com>
Project-URL: Homepage, https://github.com/mypalmike/ijsoned
Classifier: Operating System :: POSIX
Classifier: Development Status :: 4 - Beta
Classifier: Environment :: Console
Classifier: Intended Audience :: System Administrators
Classifier: License :: OSI Approved :: MIT License
Classifier: Topic :: Utilities
License-File: LICENSE
Requires-Dist: jsonpath-rw
